option_emporium/__init__.py
option_emporium/calendar_calculations.py
option_emporium-0.1.0.dist-info/METADATA
option_emporium-0.1.0.dist-info/WHEEL
option_emporium-0.1.0.dist-info/RECORD
