Metadata-Version: 2.1
Name: option-emporium
Version: 0.1.0
Summary: 
Author: Jeroen van Lier
Author-email: jeroencvlier@gmail.com
Requires-Python: >=3.12,<4.0
Classifier: Programming Language :: Python :: 3
Classifier: Programming Language :: Python :: 3.12
Classifier: Programming Language :: Python :: 3.13
Requires-Dist: loguru (>=0.7.3,<0.8.0)
Requires-Dist: pandas (>=2.2.3,<3.0.0)
Requires-Dist: pandas-market-calendars (>=4.4.2,<5.0.0)
